README.md
setup.py
openidcpy/__init__.py
openidcpy/client.py
openidcpy.egg-info/PKG-INFO
openidcpy.egg-info/SOURCES.txt
openidcpy.egg-info/dependency_links.txt
openidcpy.egg-info/requires.txt
openidcpy.egg-info/top_level.txt