Metadata-Version: 2.1
Name: openidcpy
Version: 0.7
Summary: A package that implements the Relying Party Authorization Code Flow for OpenId Connect
Home-page: https://github.com/intech-iiot/openidcpy
Author: Usman Shahid
Author-email: usman.shahid@intechww.com
License: Apache 2.0
Platform: UNKNOWN
